timereporter/__init__.py
timereporter/__main__.py
timereporter/calendar.py
timereporter/calendar_printer.py
timereporter/camel_registry.py
timereporter/commands/command.py
timereporter/commands/command_factory.py
timereporter/commands/project_command.py
timereporter/commands/redo_command.py
timereporter/commands/show_commands.py
timereporter/commands/time_reporter_command.py
timereporter/commands/undo_command.py
timereporter/date_arg_parser.py
timereporter/day.py
timereporter/mydatetime.py
timereporter/project.py
timereporter/timeparser.py
timereporter/views/browser_month_view.py
timereporter/views/browser_shower.py
timereporter/views/browser_week_view.py
timereporter/views/console_day_view.py
timereporter/views/console_month_view.py
timereporter/views/console_week_view.py
timereporter/views/day_shower.py
timereporter/views/flex_view.py
timereporter/views/view.py
timereporter/views/week_view.py
timereporter-0.1.2.dist-info/WHEEL
timereporter-0.1.2.dist-info/METADATA
timereporter-0.1.2.dist-info/RECORD
